pip_utils/__init__.py
pip_utils/__main__.py
pip_utils/cli.py
pip_utils/dependants.py
pip_utils/dependents.py
pip_utils/locate.py
pip_utils/outdated.py
pip_utils/parents.py
pip_utils-0.0.5.dist-info/DESCRIPTION.rst
pip_utils-0.0.5.dist-info/METADATA
pip_utils-0.0.5.dist-info/RECORD
pip_utils-0.0.5.dist-info/WHEEL
pip_utils-0.0.5.dist-info/entry_points.txt
pip_utils-0.0.5.dist-info/metadata.json
pip_utils-0.0.5.dist-info/top_level.txt
